envirophat/__init__.py
envirophat/ads1015.py
envirophat/bmp280.py
envirophat/i2c_bus.py
envirophat/leds.py
envirophat/lsm303d.py
envirophat/tcs3472.py
envirophat-1.0.1.dist-info/LICENSE.txt
envirophat-1.0.1.dist-info/METADATA
envirophat-1.0.1.dist-info/WHEEL
envirophat-1.0.1.dist-info/top_level.txt
envirophat-1.0.1.dist-info/RECORD
